{
  "unversionedId": "ssi/did",
  "id": "ssi/did",
  "title": "Decentralized Identifier (DID)",
  "description": "Decentralized Identifiers (W3C Decentralized Identifiers), or DIDs in short, are the new type of unique and persistent identifiers (URI) that enable verifiable and decentralized identity. They are entirely controlled by the identity owner and are independent of centralized authorities. Each individual can create as many DIDs as they wish and use each in different contexts to prevent data correlation.",
  "source": "@site/docs/ssi/did.md",
  "sourceDirName": "ssi",
  "slug": "/ssi/did",
  "permalink": "/ssi-snap-docs/docs/ssi/did",
  "draft": false,
  "editUrl": "https://github.com/blockchain-lab-um/ssi-snap-docs/edit/master/docs/ssi/did.md",
  "tags": [],
  "version": "current",
  "sidebarPosition": 2,
  "frontMatter": {
    "sidebar_position": 2
  },
  "sidebar": "tutorialSidebar",
  "previous": {
    "title": "Introduction",
    "permalink": "/ssi-snap-docs/docs/ssi/"
  },
  "next": {
    "title": "Verifiable Credentials (VC)",
    "permalink": "/ssi-snap-docs/docs/ssi/vc"
  }
}
